[
  { "id": "af", "text": "Afghanistan (افغانستان)", "dialCode": "93" },
  { "id": "al", "text": "Albania (Shqipëri)", "dialCode": "355" },
  { "id": "dz", "text": "Algeria (الجزائر‬‎)", "dialCode": "213" },
  { "id": "as", "text": "American Samoa", "dialCode": "1684" },
  { "id": "ad", "text": "Andorra", "dialCode": "376" },
  { "id": "ao", "text": "Angola", "dialCode": "244" },
  { "id": "ai", "text": "Anguilla", "dialCode": "1264" },
  { "id": "ag", "text": "Antigua and Barbuda", "dialCode": "1268" },
  { "id": "ar", "text": "Argentina", "dialCode": "54" },
  { "id": "am", "text": "Armenia (Հայաստան)", "dialCode": "374" },
  { "id": "aw", "text": "Aruba", "dialCode": "297" },
  { "id": "au", "text": "Australia", "dialCode": "61" },
  { "id": "at", "text": "Austria (Österreich)", "dialCode": "43" },
  { "id": "az", "text": "Azerbaijan (Azərbaycan)", "dialCode": "994" },
  { "id": "bs", "text": "Bahamas", "dialCode": "1242" },
  { "id": "bh", "text": "Bahrain (البحرين‬‎)", "dialCode": "973" },
  { "id": "bd", "text": "Bangladesh (বাংলাদেশ)", "dialCode": "880" },
  { "id": "bb", "text": "Barbados", "dialCode": "1246" },
  { "id": "by", "text": "Belarus (Беларусь)", "dialCode": "375" },
  { "id": "be", "text": "Belgium (België)", "dialCode": "32" },
  { "id": "bz", "text": "Belize", "dialCode": "501" },
  { "id": "bj", "text": "Benin (Bénin)", "dialCode": "229" },
  { "id": "bm", "text": "Bermuda", "dialCode": "1441" },
  { "id": "bt", "text": "Bhutan (འབྲུག)", "dialCode": "975" },
  { "id": "bo", "text": "Bolivia", "dialCode": "591" },
  { "id": "ba", "text": "Bosnia and Herzegovina (Босна и Херцеговина)", "dialCode": "387" },
  { "id": "bw", "text": "Botswana", "dialCode": "267" },
  { "id": "br", "text": "Brazil (Brasil)", "dialCode": "55" },
  { "id": "bn", "text": "Brunei", "dialCode": "673" },
  { "id": "bg", "text": "Bulgaria (България)", "dialCode": "359" },
  { "id": "bf", "text": "Burkina Faso", "dialCode": "226" },
  { "id": "bi", "text": "Burundi (Uburundi)", "dialCode": "257" },
  { "id": "kh", "text": "Cambodia (កម្ពុជា)", "dialCode": "855" },
  { "id": "cm", "text": "Cameroon (Cameroun)", "dialCode": "237" },
  { "id": "ca", "text": "Canada", "dialCode": "1" },
  { "id": "cv", "text": "Cape Verde (Kabu Verdi)", "dialCode": "238" },
  { "id": "ky", "text": "Cayman Islands", "dialCode": "1345" },
  { "id": "cf", "text": "Central African Republic (République centrafricaine)", "dialCode": "236" },
  { "id": "td", "text": "Chad (Tchad)", "dialCode": "235" },
  { "id": "cl", "text": "Chile", "dialCode": "56" },
  { "id": "cn", "text": "China (中国)", "dialCode": "86", "language": "Chinese" },
  { "id": "co", "text": "Colombia", "dialCode": "57" },
  { "id": "km", "text": "Comoros (جزر القمر‬‎)", "dialCode": "269" },
  { "id": "cd", "text": "DR Congo (Jamhuri ya Kidemokrasia ya Kongo)", "dialCode": "243" },
  { "id": "cg", "text": "Congo (Republic) (Congo-Brazzaville)", "dialCode": "242" },
  { "id": "ck", "text": "Cook Islands", "dialCode": "682" },
  { "id": "cr", "text": "Costa Rica", "dialCode": "506" },
  { "id": "ci", "text": "Côte d'Ivoire (Ivory Coast)", "dialCode": "225" },
  { "id": "hr", "text": "Croatia (Hrvatska)", "dialCode": "385" },
  { "id": "cu", "text": "Cuba", "dialCode": "53" },
  { "id": "cy", "text": "Cyprus (Κύπρος)", "dialCode": "357" },
  { "id": "cz", "text": "Czech Republic (Česká republika)", "dialCode": "420" },
  { "id": "dk", "text": "Denmark (Danmark)", "dialCode": "45" },
  { "id": "dj", "text": "Djibouti", "dialCode": "253" },
  { "id": "dm", "text": "Dominica", "dialCode": "1767" },
  { "id": "do", "text": "Dominican Republic (República Dominicana)", "dialCode": "1" },
  { "id": "tl", "text": "East Timor (Timor-Leste)", "dialCode": "670" },
  { "id": "ec", "text": "Ecuador", "dialCode": "593" },
  { "id": "eg", "text": "Egypt (مصر‬‎)", "dialCode": "20" },
  { "id": "sv", "text": "El Salvador", "dialCode": "503" },
  { "id": "gq", "text": "Equatorial Guinea (Guinea Ecuatorial)", "dialCode": "240" },
  { "id": "er", "text": "Eritrea", "dialCode": "291" },
  { "id": "ee", "text": "Estonia (Eesti)", "dialCode": "372" },
  { "id": "et", "text": "Ethiopia", "dialCode": "251" },
  { "id": "fk", "text": "Falkland Islands (Islas Malvinas)", "dialCode": "500" },
  { "id": "fo", "text": "Faroe Islands (Føroyar)", "dialCode": "298" },
  { "id": "fj", "text": "Fiji", "dialCode": "679" },
  { "id": "fi", "text": "Finland (Suomi)", "dialCode": "358" },
  { "id": "fr", "text": "France", "dialCode": "33" },
  { "id": "gf", "text": "French Guiana (Guyane française)", "dialCode": "594" },
  { "id": "pf", "text": "French Polynesia (Polynésie française)", "dialCode": "689" },
  { "id": "ga", "text": "Gabon", "dialCode": "241" },
  { "id": "gm", "text": "Gambia", "dialCode": "220" },
  { "id": "ge", "text": "Georgia (საქართველო)", "dialCode": "995" },
  { "id": "de", "text": "Germany (Deutschland)", "dialCode": "49" },
  { "id": "gh", "text": "Ghana (Gaana)", "dialCode": "233" },
  { "id": "gi", "text": "Gibraltar", "dialCode": "350" },
  { "id": "gr", "text": "Greece (Ελλάδα)", "dialCode": "30" },
  { "id": "gl", "text": "Greenland (Kalaallit Nunaat)", "dialCode": "299" },
  { "id": "gd", "text": "Grenada", "dialCode": "1473" },
  { "id": "gp", "text": "Guadeloupe", "dialCode": "590" },
  { "id": "gu", "text": "Guam", "dialCode": "1671" },
  { "id": "gt", "text": "Guatemala", "dialCode": "502" },
  { "id": "gn", "text": "Guinea (Guinée)", "dialCode": "224" },
  { "id": "gw", "text": "Guinea-Bissau (Guiné Bissau)", "dialCode": "245" },
  { "id": "gy", "text": "Guyana", "dialCode": "592" },
  { "id": "ht", "text": "Haiti", "dialCode": "509" },
  { "id": "hn", "text": "Honduras", "dialCode": "504" },
  { "id": "hk", "text": "Hong Kong (香港)", "dialCode": "852" },
  { "id": "hu", "text": "Hungary (Magyarország)", "dialCode": "36" },
  { "id": "is", "text": "Iceland (Ísland)", "dialCode": "354" },
  { "id": "in", "text": "India (भारत)", "dialCode": "91" },
  { "id": "id", "text": "Indonesia", "dialCode": "62" },
  { "id": "ir", "text": "Iran (ایران‬‎)", "dialCode": "98" },
  { "id": "iq", "text": "Iraq (العراق‬‎)", "dialCode": "964" },
  { "id": "ie", "text": "Ireland", "dialCode": "353" },
  { "id": "il", "text": "Israel (ישראל‬‎&#x202C;&lrml)", "dialCode": "972" },
  { "id": "it", "text": "Italy (Italia)", "dialCode": "39" },
  { "id": "jm", "text": "Jamaica", "dialCode": "1876" },
  { "id": "jp", "text": "Japan (日本)", "dialCode": "81", "language": "Japanese" },
  { "id": "jo", "text": "Jordan (الأردن‬‎)", "dialCode": "962" },
  { "id": "kz", "text": "Kazakhstan (Казахстан)", "dialCode": "7" },
  { "id": "ke", "text": "Kenya", "dialCode": "254" },
  { "id": "ki", "text": "Kiribati", "dialCode": "686" },
  { "id": "kw", "text": "Kuwait (الكويت‬‎‬‎)", "dialCode": "965" },
  { "id": "kg", "text": "Kyrgyzstan (Кыргызстан)", "dialCode": "996" },
  { "id": "la", "text": "Laos PDR (ລາວ)", "dialCode": "856" },
  { "id": "lv", "text": "Latvia (Latvija)", "dialCode": "371" },
  { "id": "lb", "text": "Lebanon (لبنان‬‎)", "dialCode": "961" },
  { "id": "ls", "text": "Lesotho", "dialCode": "266" },
  { "id": "lr", "text": "Liberia", "dialCode": "231" },
  { "id": "ly", "text": "Libya (ليبيا‬‎)", "dialCode": "218" },
  { "id": "li", "text": "Liechtenstein", "dialCode": "423" },
  { "id": "lt", "text": "Lithuania (Lietuva)", "dialCode": "370" },
  { "id": "lu", "text": "Luxembourg", "dialCode": "352" },
  { "id": "mo", "text": "Macau (澳門)", "dialCode": "853" },
  { "id": "mk", "text": "Macedonia (FYROM) (Македонија)", "dialCode": "389" },
  { "id": "mg", "text": "Madagascar (Madagasikara)", "dialCode": "261" },
  { "id": "mw", "text": "Malawi", "dialCode": "265" },
  { "id": "my", "text": "Malaysia", "dialCode": "60" },
  { "id": "mv", "text": "Maldives", "dialCode": "960" },
  { "id": "ml", "text": "Mali", "dialCode": "223" },
  { "id": "mt", "text": "Malta", "dialCode": "356" },
  { "id": "mh", "text": "Marshall Islands", "dialCode": "692" },
  { "id": "mq", "text": "Martinique", "dialCode": "596" },
  { "id": "mr", "text": "Mauritania (موريتانيا‬‎)", "dialCode": "222" },
  { "id": "mu", "text": "Mauritius (Moris)", "dialCode": "230" },
  { "id": "mx", "text": "Mexico (México)", "dialCode": "52" },
  { "id": "fm", "text": "Micronesia", "dialCode": "691" },
  { "id": "md", "text": "Moldova (Republica Moldova)", "dialCode": "373" },
  { "id": "mc", "text": "Monaco", "dialCode": "377" },
  { "id": "mn", "text": "Mongolia (Монгол)", "dialCode": "976" },
  { "id": "me", "text": "Montenegro (Crna Gora)", "dialCode": "382" },
  { "id": "ms", "text": "Montserrat", "dialCode": "1664" },
  { "id": "ma", "text": "Morocco (المغرب‬‎)", "dialCode": "212" },
  { "id": "mz", "text": "Mozambique (Moçambique)", "dialCode": "258" },
  { "id": "mm", "text": "Myanmar (Burma) (မြန်မာ)", "dialCode": "95" },
  { "id": "na", "text": "Namibia (Namibië)", "dialCode": "264" },
  { "id": "np", "text": "Nepal (नेपाल)", "dialCode": "977" },
  { "id": "nl", "text": "Netherlands (Nederland)", "dialCode": "31" },
  { "id": "nc", "text": "New Caledonia (Nouvelle-Calédonie)", "dialCode": "687" },
  { "id": "nz", "text": "New Zealand", "dialCode": "64" },
  { "id": "ni", "text": "Nicaragua", "dialCode": "505" },
  { "id": "ne", "text": "Niger (Nijar)", "dialCode": "227" },
  { "id": "ng", "text": "Nigeria", "dialCode": "234" },
  { "id": "nu", "text": "Niue", "dialCode": "683" },
  { "id": "nf", "text": "Norfolk Island", "dialCode": "672" },
  { "id": "no", "text": "Norway (Norge)", "dialCode": "47" },
  { "id": "om", "text": "Oman (عُمان‬‎)", "dialCode": "968" },
  { "id": "pk", "text": "Pakistan (پاکستان‬‎)", "dialCode": "92" },
  { "id": "pw", "text": "Palau", "dialCode": "680" },
  { "id": "ps", "text": "Palestine (Palestinian Territory) (فلسطين‬‎)", "dialCode": "970" },
  { "id": "pa", "text": "Panama (Panamá)", "dialCode": "507" },
  { "id": "pg", "text": "Papua New Guinea", "dialCode": "675" },
  { "id": "py", "text": "Paraguay", "dialCode": "595" },
  { "id": "pe", "text": "Peru (Perú)", "dialCode": "51" },
  { "id": "ph", "text": "Philippines", "dialCode": "63", "language": "Filipino" },
  { "id": "pl", "text": "Poland (Polska)", "dialCode": "48" },
  { "id": "pt", "text": "Portugal", "dialCode": "351" },
  { "id": "pr", "text": "Puerto Rico", "dialCode": "1" },
  { "id": "qa", "text": "Qatar (قطر‬‎)", "dialCode": "974" },
  { "id": "re", "text": "Reunion/Mayotte", "dialCode": "262" },
  { "id": "ro", "text": "Romania (România)", "dialCode": "40" },
  { "id": "ru", "text": "Russia (Россия)", "dialCode": "7", "language": "Russian" },
  { "id": "rw", "text": "Rwanda", "dialCode": "250" },
  { "id": "ws", "text": "Samoa", "dialCode": "685" },
  { "id": "sm", "text": "San Marino", "dialCode": "378" },
  {
    "id": "st",
    "text": "Sao Tome and Principe (São Tomé and Príncipe) (São Tomé e Príncipe)",
    "dialCode": "239"
  },
  { "id": "sa", "text": "Saudi Arabia (‫المملكة العربية السعودية‬‎)", "dialCode": "966" },
  { "id": "sn", "text": "Senegal (Sénégal)", "dialCode": "221" },
  { "id": "rs", "text": "Serbia (Србија)", "dialCode": "381" },
  { "id": "sc", "text": "Seychelles", "dialCode": "248" },
  { "id": "sl", "text": "Sierra Leone", "dialCode": "232" },
  { "id": "sg", "text": "Singapore", "dialCode": "65" },
  { "id": "sk", "text": "Slovakia (Slovensko)", "dialCode": "421" },
  { "id": "sb", "text": "Solomon Islands", "dialCode": "677" },
  { "id": "so", "text": "Somalia (Soomaaliya)", "dialCode": "252" },
  { "id": "za", "text": "South Africa", "dialCode": "27" },
  {
    "id": "kr",
    "text": "Republic Of Korea",
    "dialCode": "82",
    "language": "Korean"
  },
  { "id": "es", "text": "Spain (España)", "dialCode": "34", "language": "Spanish" },
  { "id": "lk", "text": "Sri Lanka (ශ්‍රී ලංකාව)", "dialCode": "94" },
  { "id": "kn", "text": "St Kitts and Nevis (Saint Kitts and Nevis)", "dialCode": "1869" },
  { "id": "lc", "text": "St Lucia (Saint Lucia)", "dialCode": "1758" },
  {
    "id": "pm",
    "text": "St Pierre and Miquelon (St Pierre and Miquelon) (Saint-Pierre-et-Miquelon)",
    "dialCode": "508"
  },
  { "id": "vc", "text": "St Vincent Grenadines (Saint Vincent and the Grenadines)", "dialCode": "1784" },
  { "id": "sd", "text": "Sudan (السودان‬‎)", "dialCode": "249" },
  { "id": "sr", "text": "Suriname", "dialCode": "597" },
  { "id": "sz", "text": "Swaziland", "dialCode": "268" },
  { "id": "se", "text": "Sweden (Sverige)", "dialCode": "46" },
  { "id": "ch", "text": "Switzerland (Schweiz)", "dialCode": "41" },
  { "id": "sy", "text": "Syria (سوريا‬‎)", "dialCode": "963" },
  { "id": "tw", "text": "Taiwan (台灣)", "dialCode": "886" },
  { "id": "tj", "text": "Tajikistan", "dialCode": "992" },
  { "id": "tz", "text": "Tanzania", "dialCode": "255" },
  { "id": "th", "text": "Thailand (ไทย)", "dialCode": "66", "language": "Thailand" },
  { "id": "tg", "text": "Togo", "dialCode": "228" },
  { "id": "to", "text": "Tonga", "dialCode": "676" },
  { "id": "tt", "text": "Trinidad and Tobago", "dialCode": "1868" },
  { "id": "tn", "text": "Tunisia (تونس‬‎)", "dialCode": "216" },
  { "id": "tr", "text": "Turkey (Türkiye)", "dialCode": "90" },
  { "id": "tm", "text": "Turkmenistan", "dialCode": "993" },
  { "id": "tc", "text": "Turks and Caicos Islands", "dialCode": "1649" },
  { "id": "tv", "text": "Tuvalu", "dialCode": "688" },
  { "id": "ug", "text": "Uganda", "dialCode": "256" },
  { "id": "ua", "text": "Ukraine (Україна)", "dialCode": "380" },
  { "id": "ae", "text": "United Arab Emirates (‫الإمارات العربية المتحدة‬‎)", "dialCode": "971" },
  { "id": "gb", "text": "United Kingdom", "dialCode": "44" },
  { "id": "us", "text": "United States", "dialCode": "1", "language": "English" },
  { "id": "uy", "text": "Uruguay", "dialCode": "598" },
  { "id": "uz", "text": "Uzbekistan (Oʻzbekiston)", "dialCode": "998" },
  { "id": "vu", "text": "Vanuatu", "dialCode": "678" },
  { "id": "ve", "text": "Venezuela", "dialCode": "58" },
  { "id": "vn", "text": "Vietnam (Việt Nam)", "dialCode": "84" },
  { "id": "vg", "text": "Virgin Islands, British", "dialCode": "1284" },
  { "id": "vi", "text": "Virgin Islands, U.S.", "dialCode": "1340" },
  { "id": "wf", "text": "Wallis and Futuna (Wallis-et-Futuna)", "dialCode": "681" },
  { "id": "ye", "text": "Yemen (اليمن‬‎)", "dialCode": "967" },
  { "id": "zm", "text": "Zambia", "dialCode": "260" },
  { "id": "zw", "text": "Zimbabwe", "dialCode": "263" }
]
